README.md
setup.py
JustWatch.egg-info/PKG-INFO
JustWatch.egg-info/SOURCES.txt
JustWatch.egg-info/dependency_links.txt
JustWatch.egg-info/requires.txt
JustWatch.egg-info/top_level.txt
justwatch/__init__.py
justwatch/justwatchapi.py