Metadata-Version: 1.1
Name: JustWatch
Version: 0.5.0
Summary: A simple api for justwatch.com
Home-page: https://github.com/dawoudt/JustWatchAPI
Author: Dawoud Tabboush
Author-email: dtabboush@gmail.com
License: MIT
Keywords: movies tv api
Platform: any
Classifier: Development Status :: 4 - Beta
Classifier: Intended Audience :: Developers
Classifier: License :: OSI Approved :: MIT License
Classifier: Operating System :: OS Independent
Classifier: Programming Language :: Python
Classifier: Programming Language :: Python :: 3
Classifier: Topic :: Software Development :: Libraries :: Python Modules
